6_schiebegrister_frequenzteiler_zaehler/6_4/6_4_b+c/jk.vhdl
library ieee;
use ieee.std_logic_1164.all;

entity jk is
	port( 
		j: in std_ulogic;
		k: in  std_ulogic;
		reset: in std_ulogic;
		clock: in std_ulogic;
		q: out std_ulogic;
		nq: out std_ulogic
	);
end jk;

architecture rtl of jk is
   signal x, nqReset: std_ulogic;
begin
   process (clock) 
   begin
      if rising_edge(clock) then 
         if reset='1' then   
            x <= '0';
            nqReset <= '1';
         elsif clock ='1' then
            nqReset <= '0';
            if (j='0' and k='0') then
               x <= x;
            elsif (j='0' and k='1') then
               x <= '0';
            elsif (j='1' and k='0') then
               x <= '1';
            elsif (j='1' and k='1') then
            	if (x='1' or x='0') then x <= (not x); else x <= '1'; end if;
            end if;
         end if;
      end if;
   end process;
   q <= x;
   nq <= (not x) xor nqReset;                  
end rtl;

6_schiebegrister_frequenzteiler_zaehler/6_4/6_4_b+c/zaehler.vhdl
library ieee;
use ieee.std_logic_1164.all;

entity zaehler is
  port (
    reset: in std_ulogic;
    clock: in std_ulogic;
    count: in std_ulogic;
    down: in std_ulogic;
    q0: out std_ulogic;
    q1: out std_ulogic
  );
end zaehler;

architecture rtl of zaehler is
	component jk
	port( 
		j: in std_ulogic;
		k: in  std_ulogic;
		reset: in std_ulogic;
		clock: in std_ulogic;
		q: out std_ulogic;
		nq: out std_ulogic
	);
  	end component;
	signal toggle, x1, x2: std_ulogic;
begin	
	FF0 : jk port map (j => count, k => count, reset => reset, clock => clock, q => x1);
	x2 <= x1 xor down;
	toggle <= x2 and count;
	FF1 : jk port map (j => toggle, k => toggle, reset => reset, clock => clock, q => q1);
	q0 <= x1;
end rtl;

6_schiebegrister_frequenzteiler_zaehler/6_4/6_4_b+c/zaehler_tb.vhdl
library ieee;
use ieee.std_logic_1164.all;

entity zaehler_tb is
end zaehler_tb;

architecture test of zaehler_tb is 
	component zaehler 
 	 port (
 	   reset: in std_ulogic;
 	   clock: in std_ulogic;
 	   count: in std_ulogic;
 	   down: in std_ulogic;
 	   q0: out std_ulogic;
 	   q1: out std_ulogic
 	 );
	end component;
	  
	signal reset, clock, count, down, q0, q1 : std_ulogic;
	  
	begin 
		VorwaertsRueckwaertsZaehler : zaehler port map (reset => reset, clock => clock, count => count, down => down, q0 => q0, q1 => q1);
		
		process begin


			count <= '1';
			down <= '0';
			------ Takt beginnt-----		
			clock <= '0';
			wait for 5 ns;
			
			clock <= '1';
			wait for 5 ns;

			------ Takt beginnt-----		
			clock <= '0';
			wait for 5 ns;
			
			clock <= '1';
			wait for 5 ns;

			------ Takt beginnt-----		
			clock <= '0';
			wait for 5 ns;
			
			clock <= '1';
			wait for 5 ns;

			------ Takt beginnt-----		
			clock <= '0';
			wait for 5 ns;
			
			clock <= '1';
			wait for 5 ns;

-----------------------------------------------warm laufen -----------------------------------------------
			
			count <= '1';
			down <= '0';
			------ Takt beginnt-----		
			clock <= '0';
			wait for 5 ns;
			
			clock <= '1';
			wait for 5 ns;

			------ Takt beginnt-----		
			clock <= '0';
			wait for 5 ns;
			
			clock <= '1';
			wait for 5 ns;

			------ Takt beginnt-----		
			clock <= '0';
			wait for 5 ns;
			
			clock <= '1';
			wait for 5 ns;

			------ Takt beginnt-----		
			clock <= '0';
			wait for 5 ns;
			
			clock <= '1';
			wait for 5 ns;

-----------------------------------------------1 runde -----------------------------------------------			

			count <= '1';
			down <= '0';
			------ Takt beginnt-----		
			clock <= '0';
			wait for 5 ns;
			
			clock <= '1';
			wait for 5 ns;

			------ Takt beginnt-----		
			clock <= '0';
			wait for 5 ns;
			
			clock <= '1';
			wait for 5 ns;

			------ Takt beginnt-----		
			clock <= '0';
			wait for 5 ns;
			
			clock <= '1';
			wait for 5 ns;

			------ Takt beginnt-----		
			clock <= '0';
			wait for 5 ns;
			
			clock <= '1';
			wait for 5 ns;

-----------------------------------------------nicht zählen -----------------------------------------------			
			
			
			count <= '0';
			down <= '0';
			------ Takt beginnt-----		
			clock <= '0';
			wait for 5 ns;
			
			clock <= '1';
			wait for 5 ns;

			------ Takt beginnt-----		
			clock <= '0';
			wait for 5 ns;
			
			clock <= '1';
			wait for 5 ns;

			------ Takt beginnt-----		
			clock <= '0';
			wait for 5 ns;
			
			clock <= '1';
			wait for 5 ns;

			------ Takt beginnt-----		
			clock <= '0';
			wait for 5 ns;
			
			clock <= '1';
			wait for 5 ns;

-----------------------------------------------2 runde -----------------------------------------------

			count <= '1';
			down <= '1';
			------ Takt beginnt-----		
			clock <= '0';
			wait for 5 ns;
			
			clock <= '1';
			wait for 5 ns;

			------ Takt beginnt-----		
			clock <= '0';
			wait for 5 ns;
			
			clock <= '1';
			wait for 5 ns;

			------ Takt beginnt-----		
			clock <= '0';
			wait for 5 ns;
			
			clock <= '1';
			wait for 5 ns;

			------ Takt beginnt-----		
			clock <= '0';
			wait for 5 ns;
			
			clock <= '1';
			wait for 5 ns;

-----------------------------------------------1 runde rückwärts -----------------------------------------------			

			count <= '1';
			down <= '1';
			------ Takt beginnt-----		
			clock <= '0';
			wait for 5 ns;
			
			clock <= '1';
			wait for 5 ns;

			------ Takt beginnt-----		
			clock <= '0';
			wait for 5 ns;
			
			clock <= '1';
			wait for 5 ns;

			------ Takt beginnt-----		
			clock <= '0';
			wait for 5 ns;
			
			clock <= '1';
			wait for 5 ns;

			------ Takt beginnt-----		
			clock <= '0';
			wait for 5 ns;
			
			clock <= '1';
			wait for 5 ns;

-----------------------------------------------2 runde rückwärts -----------------------------------------------

			count <= '0';
			down <= '1';
			------ Takt beginnt-----		
			clock <= '0';
			wait for 5 ns;
			
			clock <= '1';
			wait for 5 ns;

			------ Takt beginnt-----		
			clock <= '0';
			wait for 5 ns;
			
			clock <= '1';
			wait for 5 ns;

			------ Takt beginnt-----		
			clock <= '0';
			wait for 5 ns;
			
			clock <= '1';
			wait for 5 ns;

			------ Takt beginnt-----		
			clock <= '0';
			wait for 5 ns;
			
			clock <= '1';
			wait for 5 ns;

-----------------------------------------------rückwärts halten -----------------------------------------------

			count <= '1';
			down <= '1';
			------ Takt beginnt-----		
			clock <= '0';
			wait for 5 ns;
			
			clock <= '1';
			wait for 5 ns;

			------ Takt beginnt-----		
			clock <= '0';
			wait for 5 ns;
			
			clock <= '1';
			wait for 5 ns;

			------ Takt beginnt-----
			reset <= '1';
			clock <= '0';
			wait for 5 ns;
			
			clock <= '1';
			wait for 5 ns;

			------ Takt beginnt-----		
			clock <= '0';
			wait for 5 ns;
			
			clock <= '1';
			wait for 5 ns;


			reset <= '1';
			------ Takt beginnt-----		
			clock <= '0';
			wait for 5 ns;
			
			clock <= '1';
			wait for 5 ns;


			reset <= '1';
			------ Takt beginnt-----		
			clock <= '0';
			wait for 5 ns;
			
			clock <= '1';
			wait for 5 ns;

			count <= '1';
			down <= '0';
			reset <= '0';

----------------------------------------------- mitten in runde 3 RESETTEN  -----------------------------------------------

			
			count <= '1';
			down <= '0';
			------ Takt beginnt-----		
			clock <= '0';
			wait for 5 ns;
			
			clock <= '1';
			wait for 5 ns;

			------ Takt beginnt-----		
			clock <= '0';
			wait for 5 ns;
			
			clock <= '1';
			wait for 5 ns;

			------ Takt beginnt-----		
			clock <= '0';
			wait for 5 ns;
			
			clock <= '1';
			wait for 5 ns;

			------ Takt beginnt-----		
			clock <= '0';
			wait for 5 ns;
			
			clock <= '1';
			wait for 5 ns;

-----------------------------------------------3 runde vorwärts -----------------------------------------------


			
			count <= '1';
			down <= '0';
			------ Takt beginnt-----		
			clock <= '0';
			wait for 5 ns;
			
			clock <= '1';
			wait for 5 ns;

			------ Takt beginnt-----		
			clock <= '0';
			wait for 5 ns;
			
			clock <= '1';
			wait for 5 ns;
			
			count <= '1';
			down <= '1';

			------ Takt beginnt-----		
			clock <= '0';
			wait for 5 ns;
			
			clock <= '1';
			wait for 5 ns;

			------ Takt beginnt-----		
			clock <= '0';
			wait for 5 ns;
			
			clock <= '1';
			wait for 5 ns;

-----------------------------------------------mitten in der runde runter rechnen -----------------------------------------------


			wait;
		end process;
	end test;

6_schiebegrister_frequenzteiler_zaehler/6_4/6_4_b+c/zaehler_tb.vcd
$date
  Wed Sep 30 00:40:51 2020
$end
$version
  GHDL v0
$end
$timescale
  1 fs
$end
$scope module standard $end
$upscope $end
$scope module std_logic_1164 $end
$upscope $end
$scope module zaehler_tb $end
$var reg 1 ! reset $end
$var reg 1 " clock $end
$var reg 1 # count $end
$var reg 1 $ down $end
$var reg 1 % q0 $end
$var reg 1 & q1 $end
$scope module vorwaertsrueckwaertszaehler $end
$var reg 1 ' reset $end
$var reg 1 ( clock $end
$var reg 1 ) count $end
$var reg 1 * down $end
$var reg 1 + q0 $end
$var reg 1 , q1 $end
$var reg 1 - toggle $end
$var reg 1 . x1 $end
$var reg 1 / x2 $end
$scope module ff0 $end
$var reg 1 0 j $end
$var reg 1 1 k $end
$var reg 1 2 reset $end
$var reg 1 3 clock $end
$var reg 1 4 q $end
$var reg 1 5 nq $end
$var reg 1 6 x $end
$var reg 1 7 nqreset $end
$upscope $end
$scope module ff1 $end
$var reg 1 8 j $end
$var reg 1 9 k $end
$var reg 1 : reset $end
$var reg 1 ; clock $end
$var reg 1 < q $end
$var reg 1 = nq $end
$var reg 1 > x $end
$var reg 1 ? nqreset $end
$upscope $end
$upscope $end
$upscope $end
$enddefinitions $end
#0
U!
0"
1#
0$
U%
U&
U'
0(
1)
0*
U+
U,
U-
U.
U/
10
11
U2
03
U4
U5
U6
U7
U8
U9
U:
0;
U<
U=
U>
U?
#5000000
1"
1%
1(
1+
1-
1.
1/
13
14
05
16
07
18
19
1;
0?
#10000000
0"
0(
03
0;
#15000000
1"
0%
1&
1(
0+
1,
0-
0.
0/
13
04
15
06
08
09
1;
1<
0=
1>
#20000000
0"
0(
03
0;
#25000000
1"
1%
1(
1+
1-
1.
1/
13
14
05
16
18
19
1;
#30000000
0"
0(
03
0;
#35000000
1"
0%
0&
1(
0+
0,
0-
0.
0/
13
04
15
06
08
09
1;
0<
1=
0>
#40000000
0"
0(
03
0;
#45000000
1"
1%
1(
1+
1-
1.
1/
13
14
05
16
18
19
1;
#50000000
0"
0(
03
0;
#55000000
1"
0%
1&
1(
0+
1,
0-
0.
0/
13
04
15
06
08
09
1;
1<
0=
1>
#60000000
0"
0(
03
0;
#65000000
1"
1%
1(
1+
1-
1.
1/
13
14
05
16
18
19
1;
#70000000
0"
0(
03
0;
#75000000
1"
0%
0&
1(
0+
0,
0-
0.
0/
13
04
15
06
08
09
1;
0<
1=
0>
#80000000
0"
0(
03
0;
#85000000
1"
1%
1(
1+
1-
1.
1/
13
14
05
16
18
19
1;
#90000000
0"
0(
03
0;
#95000000
1"
0%
1&
1(
0+
1,
0-
0.
0/
13
04
15
06
08
09
1;
1<
0=
1>
#100000000
0"
0(
03
0;
#105000000
1"
1%
1(
1+
1-
1.
1/
13
14
05
16
18
19
1;
#110000000
0"
0(
03
0;
#115000000
1"
0%
0&
1(
0+
0,
0-
0.
0/
13
04
15
06
08
09
1;
0<
1=
0>
#120000000
0"
0#
0(
0)
00
01
03
0;
#125000000
1"
1(
13
1;
#130000000
0"
0(
03
0;
#135000000
1"
1(
13
1;
#140000000
0"
0(
03
0;
#145000000
1"
1(
13
1;
#150000000
0"
0(
03
0;
#155000000
1"
1(
13
1;
#160000000
0"
1#
1$
0(
1)
1*
1-
1/
10
11
03
18
19
0;
#165000000
1"
1%
1&
1(
1+
1,
0-
1.
0/
13
14
05
16
08
09
1;
1<
0=
1>
#170000000
0"
0(
03
0;
#175000000
1"
0%
1(
0+
1-
0.
1/
13
04
15
06
18
19
1;
#180000000
0"
0(
03
0;
#185000000
1"
1%
0&
1(
1+
0,
0-
1.
0/
13
14
05
16
08
09
1;
0<
1=
0>
#190000000
0"
0(
03
0;
#195000000
1"
0%
1(
0+
1-
0.
1/
13
04
15
06
18
19
1;
#200000000
0"
0(
03
0;
#205000000
1"
1%
1&
1(
1+
1,
0-
1.
0/
13
14
05
16
08
09
1;
1<
0=
1>
#210000000
0"
0(
03
0;
#215000000
1"
0%
1(
0+
1-
0.
1/
13
04
15
06
18
19
1;
#220000000
0"
0(
03
0;
#225000000
1"
1%
0&
1(
1+
0,
0-
1.
0/
13
14
05
16
08
09
1;
0<
1=
0>
#230000000
0"
0(
03
0;
#235000000
1"
0%
1(
0+
1-
0.
1/
13
04
15
06
18
19
1;
#240000000
0"
0#
0(
0)
0-
00
01
03
08
09
0;
#245000000
1"
1(
13
1;
#250000000
0"
0(
03
0;
#255000000
1"
1(
13
1;
#260000000
0"
0(
03
0;
#265000000
1"
1(
13
1;
#270000000
0"
0(
03
0;
#275000000
1"
1(
13
1;
#280000000
0"
1#
0(
1)
1-
10
11
03
18
19
0;
#285000000
1"
1%
1&
1(
1+
1,
0-
1.
0/
13
14
05
16
08
09
1;
1<
0=
1>
#290000000
0"
0(
03
0;
#295000000
1"
0%
1(
0+
1-
0.
1/
13
04
15
06
18
19
1;
#300000000
1!
0"
1'
0(
12
03
1:
0;
#305000000
1"
0&
1(
0,
13
05
17
1;
0<
0>
1?
#310000000
0"
0(
03
0;
#315000000
1"
1(
13
1;
#320000000
0"
0(
03
0;
#325000000
1"
1(
13
1;
#330000000
0"
0(
03
0;
#335000000
1"
1(
13
1;
#340000000
0!
0"
0$
0'
0(
0*
0-
0/
02
03
08
09
0:
0;
#345000000
1"
1%
1(
1+
1-
1.
1/
13
14
16
07
18
19
1;
1=
0?
#350000000
0"
0(
03
0;
#355000000
1"
0%
1&
1(
0+
1,
0-
0.
0/
13
04
15
06
08
09
1;
1<
0=
1>
#360000000
0"
0(
03
0;
#365000000
1"
1%
1(
1+
1-
1.
1/
13
14
05
16
18
19
1;
#370000000
0"
0(
03
0;
#375000000
1"
0%
0&
1(
0+
0,
0-
0.
0/
13
04
15
06
08
09
1;
0<
1=
0>
#380000000
0"
0(
03
0;
#385000000
1"
1%
1(
1+
1-
1.
1/
13
14
05
16
18
19
1;
#390000000
0"
0(
03
0;
#395000000
1"
0%
1&
1(
0+
1,
0-
0.
0/
13
04
15
06
08
09
1;
1<
0=
1>
#400000000
0"
1$
0(
1*
1-
1/
03
18
19
0;
#405000000
1"
1%
0&
1(
1+
0,
0-
1.
0/
13
14
05
16
08
09
1;
0<
1=
0>
#410000000
0"
0(
03
0;
#415000000
1"
0%
1(
0+
1-
0.
1/
13
04
15
06
18
19
1;
