6_schiebegrister_frequenzteiler_zaehler/6_3/fsm.vhdl
library ieee;
use ieee.std_logic_1164.all;

entity divideby8FSM is
  port (clock, input, reset: in STD_LOGIC;
                 y: out STD_LOGIC);
end;

architecture synth of divideby8FSM is
  type statetype is (s0, s1, s10, s101, s1010, s10101);
  signal state, nextstate: statetype;
begin
  process (state, nextstate, clock, input) begin
    if reset = '1' then state <= S0;
    elsif clock'event and input = '1' then
    	-- report "input: " & std_ulogic'image(input);
    	case state is
		when s0 => nextstate <= s1; report "0 -> 1";
 		when s1 => nextstate <= s1; report "1 -> 1";
 		when s10 => nextstate <= s101; report "10 -> 101";
 		when s101 => nextstate <= s1; report "101 -> 1";
 		when s1010 => nextstate <= s10101; report "1010 -> 10101 jaaa";
 		when s10101 => nextstate <= s1; report "10101 -> 1";
 		when others => nextstate <= s0; report "wort: 0 fehler";
	end case;     
    elsif clock'event and input = '0' then
    	case state is
    		when s0 => nextstate <= s0; report "0 -> 0";
 		when s1 => nextstate <= s10; report "1 -> 10";
 		when s10 => nextstate <= s0; report "10 -> 0";
 		when s101 => nextstate <= s1010; report "101 -> 1010";
 		when s1010 => nextstate <= s0; report "1010 -> 0";
 		when s10101 => nextstate <= s1010; report "10101 -> 1010";
 		when others => nextstate <= s0; report "wort: 0 Fehler";
	end case;
    end if;
    -- report "state: " & statetype'image(state);
    -- report "nextstate: " & statetype'image(nextstate);
    state <= nextstate;
  end process;
  
  
  process (state, nextstate) begin
  	if state = s10101 then 
		y <= '1';
	else 
		y <= '0';
	end if;
  end process;
end;

6_schiebegrister_frequenzteiler_zaehler/6_3/fsm_tb.vhdl
library ieee;
use ieee.std_logic_1164.all;

entity fsm_tb is
end fsm_tb;

architecture test of fsm_tb is 
	component divideby8FSM 
  		port (
  			clock, input, reset: in STD_LOGIC;
               	y: out STD_LOGIC
                );
	end component;
	  
	signal clock, input, reset, y : std_ulogic;
	  
	begin 
		frequenzDing : divideby8FSM port map (clock => clock, input => input, reset => reset, y => y);
		
		process begin


			reset <= '1';
			
			-- block beginn
			clock <= '0';
			wait for 5 ns;
			
			input <= '0';
			
			clock <= '1';
			wait for 5 ns;
			-- block ende
		
			reset <= '0';
		
			-- block beginn
			clock <= '0';
			wait for 5 ns;
			
			clock <= '1';
			wait for 5 ns;
			-- block ende
		
		-------------------------------------- reset % zahl beginn
		
		
			-- block beginn
			input <= '0';  -- input
			clock <= '0';
			wait for 5 ns;
			
			input <= '1';  -- input
			clock <= '1';
			wait for 5 ns;
			-- block ende

			-- block beginn
			input <= '0';  -- input
			clock <= '0';
			wait for 5 ns;
			
			input <= '1';  -- input
			clock <= '1';
			wait for 5 ns;
			-- block ende

			-- block beginn
			input <= '0';  -- input
			clock <= '0';
			wait for 5 ns;
			
			input <= '1';  -- input
			clock <= '1';
			wait for 5 ns;
			-- block ende

			----------------------------------- zahl ende

			-- block beginn
			input <= '0';  -- input
			clock <= '0';
			wait for 5 ns;
			
			input <= '0';  -- input
			clock <= '1';
			wait for 5 ns;
			-- block ende

			-- block beginn
			input <= '1';  -- input
			clock <= '0';
			wait for 5 ns;
			
			input <= '1';  -- input
			clock <= '1';
			wait for 5 ns;
			-- block ende


			wait;
		end process;
	end test;

6_schiebegrister_frequenzteiler_zaehler/6_3/AusgabeAnsehen.vcd
$date
  Tue Sep 29 21:20:59 2020
$end
$version
  GHDL v0
$end
$timescale
  1 fs
$end
$scope module standard $end
$upscope $end
$scope module std_logic_1164 $end
$upscope $end
$scope module fsm_tb $end
$var reg 1 ! clock $end
$var reg 1 " input $end
$var reg 1 # reset $end
$var reg 1 $ y $end
$scope module frequenzding $end
$var reg 1 % clock $end
$var reg 1 & input $end
$var reg 1 ' reset $end
$var reg 1 ( y $end
$comment state is not handled $end
$comment nextstate is not handled $end
$upscope $end
$upscope $end
$enddefinitions $end
#0
0!
U"
1#
0$
0%
U&
1'
0(
#5000000
1!
0"
1%
0&
#10000000
0!
0#
0%
0'
#15000000
1!
1%
#20000000
0!
0%
#25000000
1!
1"
1%
1&
#30000000
0!
0"
0%
0&
#35000000
1!
1"
1%
1&
#40000000
0!
0"
0%
0&
#45000000
1!
1"
1$
1%
1&
1(
#50000000
0!
0"
0$
0%
0&
0(
#55000000
1!
1%
#60000000
0!
1"
0%
1&
