6_schiebegrister_frequenzteiler_zaehler/6_1/6_1_b+c/dFF.vhdl
library ieee;
use ieee.std_logic_1164.all;

entity dFF is
  port (
    clk: in std_ulogic;
    d: in std_ulogic;
    reset: in std_ulogic;
    q: out std_ulogic;
    nq: out std_ulogic
  );
end dFF;

architecture rtl of dFF is
signal zwischenQ : std_ulogic;
begin
 process(clk, zwischenQ)
 begin 
    if(rising_edge(clk)) then
    	if(reset = '1') then 
    		zwischenQ <= '0';
    	else 
     		zwischenQ <= d;
     	end if;
    end if;       
 end process;
 
 q <= zwischenQ;
 nq <= not zwischenQ; 
     
end rtl;

6_schiebegrister_frequenzteiler_zaehler/6_1/6_1_b+c/piso.vhdl
library ieee;
use ieee.std_logic_1164.all;

-- es wird zum laden und rausscheiben ein mux simuliert, dieser benutz shiftOrLoad als eingabe
-- danach wird jeweils eine sX variable gesetzt die feststellt ob das ergebnis aus dem ScheibeRegister geschoben werden soll
-- sollte das ScheibeRegster aber im lade modus sein wird die l1 variable aktiv 
-- die xX Variable ist dann das input in den FlipFlop
-- und eX ist das Ergebnis


entity piso is
  port (
    clock: in std_ulogic;
    clear: in std_ulogic;
    loadOrShift: in std_ulogic;
    b0: in std_ulogic;
    b1: in std_ulogic;
    b2: in std_ulogic;
    b3: in std_ulogic;
    b4: in std_ulogic;
    b5: in std_ulogic;
    b6: in std_ulogic;
    b7: in std_ulogic;
    q: out std_ulogic
  );
end piso;

architecture rtl of piso is
	component dFF
		  port (
    			clk: in std_ulogic;
   			d: in std_ulogic;
    			reset: in std_ulogic;
    			q: out std_ulogic;
    			nq: out std_ulogic
  		);
  	end component;
	signal x1, x2, x3, x4, x5, x6, x7, x8 : std_ulogic; 
	signal s1, s2, s3, s4, s5, s6, s7, s8 : std_ulogic; 
	signal l1, l2, l3, l4, l5, l6, l7, l8 : std_ulogic; 
	signal e1, e2, e3, e4, e5, e6, e7, e8 : std_ulogic;
	signal shift, load, output : std_ulogic;
begin
	load <= loadOrShift;
	shift <= not loadOrShift;
	
	l1 <= b1 and load;
	l2 <= b2 and load;
	l3 <= b3 and load;
	l4 <= b4 and load;
	l5 <= b5 and load;
	l6 <= b6 and load;
	l7 <= b7 and load;

	s1 <= e1 and shift;
	s2 <= e2 and shift;
	s3 <= e3 and shift;
	s4 <= e4 and shift;
	s5 <= e5 and shift;
	s6 <= e6 and shift;
	s7 <= e7 and shift;

	x1 <= l1 or s1;
	x2 <= l2 or s2;
	x3 <= l3 or s3;
	x4 <= l4 or s4;
	x5 <= l5 or s5;
	x6 <= l6 or s6;
	x7 <= l7 or s7;


	FF1 : dFF port map (clk => clock, d => b0, reset => clear, q => e1);
	FF2 : dFF port map (clk => clock, d => x1, reset => clear, q => e2);
	FF3 : dFF port map (clk => clock, d => x2, reset => clear, q => e3);
	FF4 : dFF port map (clk => clock, d => x3, reset => clear, q => e4);
	FF5 : dFF port map (clk => clock, d => x4, reset => clear, q => e5);
	FF6 : dFF port map (clk => clock, d => x5, reset => clear, q => e6);
	FF7 : dFF port map (clk => clock, d => x6, reset => clear, q => e7);
	FF8 : dFF port map (clk => clock, d => x7, reset => clear, q => output);
	
	q <= output;

end rtl;

6_schiebegrister_frequenzteiler_zaehler/6_1/6_1_b+c/piso_tb.vhdl
library ieee;
use ieee.std_logic_1164.all;

entity piso_tb is
end piso_tb;

architecture test of piso_tb is 
	component piso 
	  port (
	    clock: in std_ulogic;
	    clear: in std_ulogic;
	    loadOrShift: in std_ulogic;
	    b0: in std_ulogic;
	    b1: in std_ulogic;
	    b2: in std_ulogic;
	    b3: in std_ulogic;
	    b4: in std_ulogic;
	    b5: in std_ulogic;
	    b6: in std_ulogic;
	    b7: in std_ulogic;
	    q: out std_ulogic
	  );
	end component;
	  
	signal clock, clear, loadOrShift, b0, b1, b2, b3, b4, b5, b6, b7, q : std_ulogic;
	  
	begin 
		SchiebeRegister : piso port map (clock => clock, clear => clear, loadOrShift => loadOrShift , b0 => b0, b1 => b1, b2 => b2, b3 => b3, b4 => b4, b5 => b5, b6 => b6, b7 => b7, q => q);
		
		process begin
			
			
			b0 <= '1';
			b1 <= '1';
			b2 <= '0';
			b3 <= '1';
			b4 <= '0';
			b5 <= '0';
			b6 <= '1';
			b7 <= '1';
			loadOrShift <= '1';
			
			-- block beginn
			clock <= '0';
			wait for 5 ns;
			
			clock <= '1';
			wait for 5 ns;
			-- block ende
			
			-- block beginn
			clock <= '0';
			wait for 5 ns;
			
			clock <= '1';
			wait for 5 ns;
			-- block ende
			
			b0 <= '0';
			loadOrShift <= '0';
			
			-- block beginn
			clock <= '0';
			wait for 5 ns;
			
			clock <= '1';
			wait for 5 ns;
			-- block ende
			
			
			-- block beginn
			clock <= '0';
			wait for 5 ns;
			
			clock <= '1';
			wait for 5 ns;
			-- block ende
			
			-- block beginn
			clock <= '0';
			wait for 5 ns;
			
			clock <= '1';
			wait for 5 ns;
			-- block ende
			
			-- block beginn
			clock <= '0';
			wait for 5 ns;
			
			clock <= '1';
			wait for 5 ns;
			-- block ende
			
			-- block beginn
			clock <= '0';
			wait for 5 ns;
			
			clock <= '1';
			wait for 5 ns;
			-- block ende
			
			-- block beginn
			clock <= '0';
			wait for 5 ns;
			
			clock <= '1';
			wait for 5 ns;
			-- block ende
			
			b0 <= '0';
			b1 <= '0';
			b2 <= '0';
			b3 <= '0';
			b4 <= '0';
			b5 <= '0';
			b6 <= '0';
			b7 <= '0';
			loadOrShift <= '1';
			
			-- block beginn
			clock <= '0';
			wait for 5 ns;
			
			clock <= '1';
			wait for 5 ns;
			-- block ende
			
			b0 <= '1';
			b1 <= '0';
			b2 <= '1';
			b3 <= '0';
			b4 <= '1';
			b5 <= '0';
			b6 <= '1';
			b7 <= '0';
			
			-- block beginn
			clock <= '0';
			wait for 5 ns;
			
			clock <= '1';
			wait for 5 ns;
			-- block ende
			
			b0 <= '0';
			loadOrShift <= '0';
			
			-- block beginn
			clock <= '0';
			wait for 5 ns;
			
			clock <= '1';
			wait for 5 ns;
			-- block ende
			
			-- block beginn
			clock <= '0';
			wait for 5 ns;
			
			clock <= '1';
			wait for 5 ns;
			-- block ende
			
			-- block beginn
			clock <= '0';
			wait for 5 ns;
			
			clock <= '1';
			wait for 5 ns;
			-- block ende
			
			-- block beginn
			clock <= '0';
			wait for 5 ns;
			
			clock <= '1';
			wait for 5 ns;
			-- block ende
			
			-- block beginn
			clock <= '0';
			wait for 5 ns;
			
			clock <= '1';
			wait for 5 ns;
			-- block ende
			
			-- block beginn
			clock <= '0';
			wait for 5 ns;
			
			clock <= '1';
			wait for 5 ns;
			-- block ende
			
			-- block beginn
			clock <= '0';
			wait for 5 ns;
			
			clock <= '1';
			wait for 5 ns;
			-- block ende
			
			-- block beginn
			clock <= '0';
			wait for 5 ns;
			
			clock <= '1';
			wait for 5 ns;
			-- block ende
			
			-- block beginn
			clock <= '0';
			wait for 5 ns;
			
			clock <= '1';
			wait for 5 ns;
			-- block ende
			
			-- block beginn
			clock <= '0';
			wait for 5 ns;
			
			clock <= '1';
			wait for 5 ns;
			-- block ende
			
			-- block beginn
			clock <= '0';
			wait for 5 ns;
			
			clock <= '1';
			wait for 5 ns;
			-- block ende
			
			-- block beginn
			clock <= '0';
			wait for 5 ns;
			
			clock <= '1';
			wait for 5 ns;
			-- block ende
			
			-- block beginn
			clock <= '0';
			wait for 5 ns;
			
			clock <= '1';
			wait for 5 ns;
			-- block ende
			
			-- block beginn
			clock <= '0';
			wait for 5 ns;
			
			clock <= '1';
			wait for 5 ns;
			-- block ende
			
			-- block beginn
			clock <= '0';
			wait for 5 ns;
			
			clock <= '1';
			wait for 5 ns;
			-- block ende
			
			-- block beginn
			clock <= '0';
			wait for 5 ns;
			
			clock <= '1';
			wait for 5 ns;
			-- block ende
			

			wait;
		end process;
	end test;

6_schiebegrister_frequenzteiler_zaehler/6_1/6_1_b+c/6_1_c.vcd
$date
  Tue Sep 29 15:53:56 2020
$end
$version
  GHDL v0
$end
$timescale
  1 fs
$end
$scope module standard $end
$upscope $end
$scope module std_logic_1164 $end
$upscope $end
$scope module piso_tb $end
$var reg 1 ! clock $end
$var reg 1 " clear $end
$var reg 1 # loadorshift $end
$var reg 1 $ b0 $end
$var reg 1 % b1 $end
$var reg 1 & b2 $end
$var reg 1 ' b3 $end
$var reg 1 ( b4 $end
$var reg 1 ) b5 $end
$var reg 1 * b6 $end
$var reg 1 + b7 $end
$var reg 1 , q $end
$scope module schieberegister $end
$var reg 1 - clock $end
$var reg 1 . clear $end
$var reg 1 / loadorshift $end
$var reg 1 0 b0 $end
$var reg 1 1 b1 $end
$var reg 1 2 b2 $end
$var reg 1 3 b3 $end
$var reg 1 4 b4 $end
$var reg 1 5 b5 $end
$var reg 1 6 b6 $end
$var reg 1 7 b7 $end
$var reg 1 8 q $end
$var reg 1 9 x1 $end
$var reg 1 : x2 $end
$var reg 1 ; x3 $end
$var reg 1 < x4 $end
$var reg 1 = x5 $end
$var reg 1 > x6 $end
$var reg 1 ? x7 $end
$var reg 1 @ x8 $end
$var reg 1 A s1 $end
$var reg 1 B s2 $end
$var reg 1 C s3 $end
$var reg 1 D s4 $end
$var reg 1 E s5 $end
$var reg 1 F s6 $end
$var reg 1 G s7 $end
$var reg 1 H s8 $end
$var reg 1 I l1 $end
$var reg 1 J l2 $end
$var reg 1 K l3 $end
$var reg 1 L l4 $end
$var reg 1 M l5 $end
$var reg 1 N l6 $end
$var reg 1 O l7 $end
$var reg 1 P l8 $end
$var reg 1 Q e1 $end
$var reg 1 R e2 $end
$var reg 1 S e3 $end
$var reg 1 T e4 $end
$var reg 1 U e5 $end
$var reg 1 V e6 $end
$var reg 1 W e7 $end
$var reg 1 X e8 $end
$var reg 1 Y shift $end
$var reg 1 Z load $end
$var reg 1 [ output $end
$scope module ff1 $end
$var reg 1 \ clk $end
$var reg 1 ] d $end
$var reg 1 ^ reset $end
$var reg 1 _ q $end
$var reg 1 ` nq $end
$var reg 1 a zwischenq $end
$upscope $end
$scope module ff2 $end
$var reg 1 b clk $end
$var reg 1 c d $end
$var reg 1 d reset $end
$var reg 1 e q $end
$var reg 1 f nq $end
$var reg 1 g zwischenq $end
$upscope $end
$scope module ff3 $end
$var reg 1 h clk $end
$var reg 1 i d $end
$var reg 1 j reset $end
$var reg 1 k q $end
$var reg 1 l nq $end
$var reg 1 m zwischenq $end
$upscope $end
$scope module ff4 $end
$var reg 1 n clk $end
$var reg 1 o d $end
$var reg 1 p reset $end
$var reg 1 q q $end
$var reg 1 r nq $end
$var reg 1 s zwischenq $end
$upscope $end
$scope module ff5 $end
$var reg 1 t clk $end
$var reg 1 u d $end
$var reg 1 v reset $end
$var reg 1 w q $end
$var reg 1 x nq $end
$var reg 1 y zwischenq $end
$upscope $end
$scope module ff6 $end
$var reg 1 z clk $end
$var reg 1 { d $end
$var reg 1 | reset $end
$var reg 1 } q $end
$var reg 1 !" nq $end
$var reg 1 "" zwischenq $end
$upscope $end
$scope module ff7 $end
$var reg 1 #" clk $end
$var reg 1 $" d $end
$var reg 1 %" reset $end
$var reg 1 &" q $end
$var reg 1 '" nq $end
$var reg 1 (" zwischenq $end
$upscope $end
$scope module ff8 $end
$var reg 1 )" clk $end
$var reg 1 *" d $end
$var reg 1 +" reset $end
$var reg 1 ," q $end
$var reg 1 -" nq $end
$var reg 1 ." zwischenq $end
$upscope $end
$upscope $end
$upscope $end
$enddefinitions $end
#0
0!
U"
1#
1$
1%
0&
1'
0(
0)
1*
1+
U,
0-
U.
1/
10
11
02
13
04
05
16
17
U8
19
0:
1;
0<
0=
1>
1?
U@
0A
0B
0C
0D
0E
0F
0G
UH
1I
0J
1K
0L
0M
1N
1O
UP
UQ
UR
US
UT
UU
UV
UW
UX
0Y
1Z
U[
0\
1]
U^
U_
U`
Ua
0b
1c
Ud
Ue
Uf
Ug
0h
0i
Uj
Uk
Ul
Um
0n
1o
Up
Uq
Ur
Us
0t
0u
Uv
Uw
Ux
Uy
0z
0{
U|
U}
U!"
U""
0#"
1$"
U%"
U&"
U'"
U("
0)"
1*"
U+"
U,"
U-"
U."
#5000000
1!
1,
1-
18
1Q
1R
0S
1T
0U
0V
1W
1[
1\
1_
0`
1a
1b
1e
0f
1g
1h
0k
1l
0m
1n
1q
0r
1s
1t
0w
1x
0y
1z
0}
1!"
0""
1#"
1&"
0'"
1("
1)"
1,"
0-"
1."
#10000000
0!
0-
0\
0b
0h
0n
0t
0z
0#"
0)"
#15000000
1!
1-
1\
1b
1h
1n
1t
1z
1#"
1)"
#20000000
0!
0#
0$
0-
0/
00
1:
0;
1<
0>
1A
1B
1D
1G
0I
0K
0N
0O
1Y
0Z
0\
0]
0b
0h
1i
0n
0o
0t
1u
0z
0#"
0$"
0)"
#25000000
1!
1-
09
1;
0<
1=
0?
0A
1C
0D
1E
0G
0Q
1S
0T
1U
0W
1\
0_
1`
0a
1b
0c
1h
1k
0l
1m
1n
1o
0q
1r
0s
1t
0u
1w
0x
1y
1z
1{
1#"
0&"
1'"
0("
1)"
0*"
#30000000
0!
0-
0\
0b
0h
0n
0t
0z
0#"
0)"
#35000000
1!
0,
1-
08
0:
1<
0=
1>
0B
1D
0E
1F
0R
1T
0U
1V
0[
1\
1b
0e
1f
0g
1h
0i
1n
1q
0r
1s
1t
1u
0w
1x
0y
1z
0{
1}
0!"
1""
1#"
1$"
1)"
0,"
1-"
0."
#40000000
0!
0-
0\
0b
0h
0n
0t
0z
0#"
0)"
#45000000
1!
1-
0;
1=
0>
1?
0C
1E
0F
1G
0S
1U
0V
1W
1\
1b
1h
0k
1l
0m
1n
0o
1t
1w
0x
1y
1z
1{
0}
1!"
0""
1#"
0$"
1&"
0'"
1("
1)"
1*"
#50000000
0!
0-
0\
0b
0h
0n
0t
0z
0#"
0)"
#55000000
1!
1,
1-
18
0<
1>
0?
0D
1F
0G
0T
1V
0W
1[
1\
1b
1h
1n
0q
1r
0s
1t
0u
1z
1}
0!"
1""
1#"
1$"
0&"
1'"
0("
1)"
0*"
1,"
0-"
1."
#60000000
0!
0-
0\
0b
0h
0n
0t
0z
0#"
0)"
#65000000
1!
0,
1-
08
0=
1?
0E
1G
0U
1W
0[
1\
1b
1h
1n
1t
0w
1x
0y
1z
0{
1#"
1&"
0'"
1("
1)"
1*"
0,"
1-"
0."
#70000000
0!
0-
0\
0b
0h
0n
0t
0z
0#"
0)"
#75000000
1!
1,
1-
18
0>
0F
0V
1[
1\
1b
1h
1n
1t
1z
0}
1!"
0""
1#"
0$"
1)"
1,"
0-"
1."
#80000000
0!
1#
0%
0'
0*
0+
0-
1/
01
03
06
07
0?
0G
0Y
1Z
0\
0b
0h
0n
0t
0z
0#"
0)"
0*"
#85000000
1!
0,
1-
08
0W
0[
1\
1b
1h
1n
1t
1z
1#"
0&"
1'"
0("
1)"
0,"
1-"
0."
#90000000
0!
1$
1&
1(
1*
0-
10
12
14
16
1:
1<
1>
1J
1L
1N
0\
1]
0b
0h
1i
0n
0t
1u
0z
0#"
1$"
0)"
#95000000
1!
1-
1Q
1S
1U
1W
1\
1_
0`
1a
1b
1h
1k
0l
1m
1n
1t
1w
0x
1y
1z
1#"
1&"
0'"
1("
1)"
#100000000
0!
0#
0$
0-
0/
00
19
0:
1;
0<
1=
0>
1?
1A
1C
1E
1G
0J
0L
0N
1Y
0Z
0\
0]
0b
1c
0h
0i
0n
1o
0t
0u
0z
1{
0#"
0$"
0)"
1*"
#105000000
1!
1,
1-
18
09
1:
0;
1<
0=
1>
0?
0A
1B
0C
1D
0E
1F
0G
0Q
1R
0S
1T
0U
1V
0W
1[
1\
0_
1`
0a
1b
0c
1e
0f
1g
1h
1i
0k
1l
0m
1n
0o
1q
0r
1s
1t
1u
0w
1x
0y
1z
0{
1}
0!"
1""
1#"
1$"
0&"
1'"
0("
1)"
0*"
1,"
0-"
1."
#110000000
0!
0-
0\
0b
0h
0n
0t
0z
0#"
0)"
#115000000
1!
0,
1-
08
0:
1;
0<
1=
0>
1?
0B
1C
0D
1E
0F
1G
0R
1S
0T
1U
0V
1W
0[
1\
1b
0e
1f
0g
1h
0i
1k
0l
1m
1n
1o
0q
1r
0s
1t
0u
1w
0x
1y
1z
1{
0}
1!"
0""
1#"
0$"
1&"
0'"
1("
1)"
1*"
0,"
1-"
0."
#120000000
0!
0-
0\
0b
0h
0n
0t
0z
0#"
0)"
#125000000
1!
1,
1-
18
0;
1<
0=
1>
0?
0C
1D
0E
1F
0G
0S
1T
0U
1V
0W
1[
1\
1b
1h
0k
1l
0m
1n
0o
1q
0r
1s
1t
1u
0w
1x
0y
1z
0{
1}
0!"
1""
1#"
1$"
0&"
1'"
0("
1)"
0*"
1,"
0-"
1."
#130000000
0!
0-
0\
0b
0h
0n
0t
0z
0#"
0)"
#135000000
1!
0,
1-
08
0<
1=
0>
1?
0D
1E
0F
1G
0T
1U
0V
1W
0[
1\
1b
1h
1n
0q
1r
0s
1t
0u
1w
0x
1y
1z
1{
0}
1!"
0""
1#"
0$"
1&"
0'"
1("
1)"
1*"
0,"
1-"
0."
#140000000
0!
0-
0\
0b
0h
0n
0t
0z
0#"
0)"
#145000000
1!
1,
1-
18
0=
1>
0?
0E
1F
0G
0U
1V
0W
1[
1\
1b
1h
1n
1t
0w
1x
0y
1z
0{
1}
0!"
1""
1#"
1$"
0&"
1'"
0("
1)"
0*"
1,"
0-"
1."
#150000000
0!
0-
0\
0b
0h
0n
0t
0z
0#"
0)"
#155000000
1!
0,
1-
08
0>
1?
0F
1G
0V
1W
0[
1\
1b
1h
1n
1t
1z
0}
1!"
0""
1#"
0$"
1&"
0'"
1("
1)"
1*"
0,"
1-"
0."
#160000000
0!
0-
0\
0b
0h
0n
0t
0z
0#"
0)"
#165000000
1!
1,
1-
18
0?
0G
0W
1[
1\
1b
1h
1n
1t
1z
1#"
0&"
1'"
0("
1)"
0*"
1,"
0-"
1."
#170000000
0!
0-
0\
0b
0h
0n
0t
0z
0#"
0)"
#175000000
1!
0,
1-
08
0[
1\
1b
1h
1n
1t
1z
1#"
1)"
0,"
1-"
0."
