6_schiebegrister_frequenzteiler_zaehler/6_2/6_2_c/fsm.vhdl
library ieee;
use ieee.std_logic_1164.all;

entity divideby8FSM is
  port (clk, reset: in STD_LOGIC;
                 y: out STD_LOGIC);
end;

architecture synth of divideby8FSM is
  type statetype is (s0, s1, s2, s3, s4, s5, s6, s7);
  signal state, nextstate: statetype;
begin
  -- state register
  process (clk, reset) begin
    if reset = '1' then state <= S0;
    elsif clk'event and clk = '1' then
      state <= nextstate;
    end if;
  end process;

  process (state) begin
  	case state is
		when s0 => nextstate <= s1; y <= '0';
 		when s1 => nextstate <= s2; y <= '0';
 		when s2 => nextstate <= s3; y <= '0';
 		when s3 => nextstate <= s4; y <= '0';
 		when s4 => nextstate <= s5; y <= '0';
 		when s5 => nextstate <= s6; y <= '0';
 		when s6 => nextstate <= s7; y <= '0';
 		when s7 => nextstate <= s0; y <= '1';
 		when others => nextstate <= s0;
	end case;  
  end process;
end;

6_schiebegrister_frequenzteiler_zaehler/6_2/6_2_c/fsm_tb.vhdl
library ieee;
use ieee.std_logic_1164.all;

entity fsm_tb is
end fsm_tb;

architecture test of fsm_tb is 
	component divideby8FSM 
  		port (
  			clk, reset: in STD_LOGIC;
               	y: out STD_LOGIC
                );
	end component;
	  
	signal clk, reset, y : std_ulogic;
	  
	begin 
		frequenzDing : divideby8FSM port map (clk => clk, reset => reset, y => y);
		
		process begin


			reset <= '1';
			
			-- block beginn
			clk <= '0';
			wait for 5 ns;
			
			clk <= '1';
			wait for 5 ns;
			-- block ende
			
			reset <= '0';

			-- block beginn
			clk <= '0';
			wait for 5 ns;
			
			clk <= '1';
			wait for 5 ns;
			-- block ende
			
			-- block beginn
			clk <= '0';
			wait for 5 ns;
			
			clk <= '1';
			wait for 5 ns;
			-- block ende
			
			-- block beginn
			clk <= '0';
			wait for 5 ns;
			
			clk <= '1';
			wait for 5 ns;
			-- block ende
			
			-- block beginn
			clk <= '0';
			wait for 5 ns;
			
			clk <= '1';
			wait for 5 ns;
			-- block ende
			
			-- block beginn
			clk <= '0';
			wait for 5 ns;
			
			clk <= '1';
			wait for 5 ns;
			-- block ende
			
			-- block beginn
			clk <= '0';
			wait for 5 ns;
			
			clk <= '1';
			wait for 5 ns;
			-- block ende
			
			-- block beginn
			clk <= '0';
			wait for 5 ns;
			
			clk <= '1';
			wait for 5 ns;
			-- block ende
			
			-- block beginn
			clk <= '0';
			wait for 5 ns;
			
			clk <= '1';
			wait for 5 ns;
			-- block ende
			
			-- block beginn
			clk <= '0';
			wait for 5 ns;
			
			clk <= '1';
			wait for 5 ns;
			-- block ende
			
			-- block beginn
			clk <= '0';
			wait for 5 ns;
			
			clk <= '1';
			wait for 5 ns;
			-- block ende
			
			-- block beginn
			clk <= '0';
			wait for 5 ns;
			
			clk <= '1';
			wait for 5 ns;
			-- block ende
			
			-- block beginn
			clk <= '0';
			wait for 5 ns;
			
			clk <= '1';
			wait for 5 ns;
			-- block ende
			
			-- block beginn
			clk <= '0';
			wait for 5 ns;
			
			clk <= '1';
			wait for 5 ns;
			-- block ende
			
			-- block beginn
			clk <= '0';
			wait for 5 ns;
			
			clk <= '1';
			wait for 5 ns;
			-- block ende
			
			-- block beginn
			clk <= '0';
			wait for 5 ns;
			
			clk <= '1';
			wait for 5 ns;
			-- block ende
			
			-- block beginn
			clk <= '0';
			wait for 5 ns;
			
			clk <= '1';
			wait for 5 ns;
			-- block ende
			
			-- block beginn
			clk <= '0';
			wait for 5 ns;
			
			clk <= '1';
			wait for 5 ns;
			-- block ende
			
			-- block beginn
			clk <= '0';
			wait for 5 ns;
			
			clk <= '1';
			wait for 5 ns;
			-- block ende
			
			-- block beginn
			clk <= '0';
			wait for 5 ns;
			
			clk <= '1';
			wait for 5 ns;
			-- block ende
			
			-- block beginn
			clk <= '0';
			wait for 5 ns;
			
			clk <= '1';
			wait for 5 ns;
			-- block ende
			
			-- block beginn
			clk <= '0';
			wait for 5 ns;
			
			clk <= '1';
			wait for 5 ns;
			-- block ende
			
			-- block beginn
			clk <= '0';
			wait for 5 ns;
			
			clk <= '1';
			wait for 5 ns;
			-- block ende
			
			-- block beginn
			clk <= '0';
			wait for 5 ns;
			
			clk <= '1';
			wait for 5 ns;
			-- block ende
			
			-- block beginn
			clk <= '0';
			wait for 5 ns;
			
			clk <= '1';
			wait for 5 ns;
			-- block ende
			

			
			wait;
		end process;
	end test;

6_schiebegrister_frequenzteiler_zaehler/6_2/6_2_c/6_2_c.vcd
$date
  Tue Sep 29 17:25:48 2020
$end
$version
  GHDL v0
$end
$timescale
  1 fs
$end
$scope module standard $end
$upscope $end
$scope module std_logic_1164 $end
$upscope $end
$scope module fsm_tb $end
$var reg 1 ! clk $end
$var reg 1 " reset $end
$var reg 1 # y $end
$scope module frequenzding $end
$var reg 1 $ clk $end
$var reg 1 % reset $end
$var reg 1 & y $end
$comment state is not handled $end
$comment nextstate is not handled $end
$upscope $end
$upscope $end
$enddefinitions $end
#0
0!
1"
0#
0$
1%
0&
#5000000
1!
1$
#10000000
0!
0"
0$
0%
#15000000
1!
1$
#20000000
0!
0$
#25000000
1!
1$
#30000000
0!
0$
#35000000
1!
1$
#40000000
0!
0$
#45000000
1!
1$
#50000000
0!
0$
#55000000
1!
1$
#60000000
0!
0$
#65000000
1!
1$
#70000000
0!
0$
#75000000
1!
1#
1$
1&
#80000000
0!
0$
#85000000
1!
0#
1$
0&
#90000000
0!
0$
#95000000
1!
1$
#100000000
0!
0$
#105000000
1!
1$
#110000000
0!
0$
#115000000
1!
1$
#120000000
0!
0$
#125000000
1!
1$
#130000000
0!
0$
#135000000
1!
1$
#140000000
0!
0$
#145000000
1!
1$
#150000000
0!
0$
#155000000
1!
1#
1$
1&
#160000000
0!
0$
#165000000
1!
0#
1$
0&
#170000000
0!
0$
#175000000
1!
1$
#180000000
0!
0$
#185000000
1!
1$
#190000000
0!
0$
#195000000
1!
1$
#200000000
0!
0$
#205000000
1!
1$
#210000000
0!
0$
#215000000
1!
1$
#220000000
0!
0$
#225000000
1!
1$
#230000000
0!
0$
#235000000
1!
1#
1$
1&
#240000000
0!
0$
#245000000
1!
0#
1$
0&
